data_snapshot/__init__.py
data_snapshot/extract_snapshots.py
data_snapshot-0.1.0.dist-info/LICENSE
data_snapshot-0.1.0.dist-info/METADATA
data_snapshot-0.1.0.dist-info/WHEEL
data_snapshot-0.1.0.dist-info/RECORD
